MANIFEST.in
README.md
setup.py
leexportpy/__init__.py
leexportpy/_version.py
leexportpy/leexport.py
leexportpy/lerestresponse.py
leexportpy/queryresponse.py
leexportpy/request_helper.py
leexportpy/search.py
leexportpy/service.py
leexportpy.egg-info/PKG-INFO
leexportpy.egg-info/SOURCES.txt
leexportpy.egg-info/dependency_links.txt
leexportpy.egg-info/entry_points.txt
leexportpy.egg-info/not-zip-safe
leexportpy.egg-info/requires.txt
leexportpy.egg-info/top_level.txt
leexportpy/services/__init__.py
leexportpy/services/dummy_service.py
leexportpy/services/geckoboard_service.py
leexportpy/services/hosted_graphite_service.py
leexportpy/services/kafka_service.py