Metadata-Version: 1.0
Name: leexportpy
Version: 0.1.8
Summary: Logentries by Rapid7 log export proxy for external systems.
Home-page: https://github.com/logentries/leexportpy
Author: Safa Topal
Author-email: Safa_Topal@rapid7.com
License: MIT
Platform: UNKNOWN
